package_demo/Demo.py
package_demo/Jiaoben.py
package_demo/__init__.py
RAGCheckerZsV2-0.1.0.dist-info/LICENSE
RAGCheckerZsV2-0.1.0.dist-info/METADATA
RAGCheckerZsV2-0.1.0.dist-info/WHEEL
RAGCheckerZsV2-0.1.0.dist-info/top_level.txt
RAGCheckerZsV2-0.1.0.dist-info/RECORD
