Metadata-Version: 2.1
Name: RAGCheckerZsV2
Version: 0.1.0
Summary: A RAG Checker Python package
Home-page: https://github.com/amazon-science/RAGChecker
Author: john_doe.2024
Author-email: 2043389890@qq.com
Classifier: Programming Language :: Python :: 3
Classifier: License :: OSI Approved :: MIT License
Classifier: Operating System :: OS Independent
Requires-Python: >=3.6
License-File: LICENSE
Requires-Dist: requests
Requires-Dist: pandas
Requires-Dist: openai
